ai_security_mcp/__init__.py
ai_security_mcp/main.py
ai_security_mcp/agents/__init__.py
ai_security_mcp/utils/__init__.py
ai_security_mcp-1.0.32.dist-info/METADATA
ai_security_mcp-1.0.32.dist-info/WHEEL
ai_security_mcp-1.0.32.dist-info/entry_points.txt
ai_security_mcp-1.0.32.dist-info/top_level.txt
ai_security_mcp-1.0.32.dist-info/RECORD
