Metadata-Version: 2.4
Name: ai-security-mcp
Version: 1.0.32
Summary: Thin client MCP server for AI Security Scanner - connects to cloud-hosted 27 agents (100% OWASP coverage)
Home-page: https://github.com/davidmatousek/CISO_Agent
Author: AI Security Team
Author-email: AI Security Team <security@ai-threat-scanner.com>
Maintainer: AI Security Team
Maintainer-email: security@ai-threat-scanner.com
Project-URL: Homepage, https://ai-threat-scanner.com
Project-URL: Documentation, https://ai-threat-scanner.com/docs
Project-URL: Repository, https://github.com/ai-security-scanner/ai-security-mcp
Project-URL: Bug Reports, https://github.com/ai-security-scanner/ai-security-mcp/issues
Keywords: security,ai,agentic,llm,owasp,vulnerability,scanner,mcp,claude,claude-code,agent,multi-agent,asi,prompt-injection,cybersecurity,devsecops,static-analysis,security-testing
Platform: any
Classifier: Development Status :: 5 - Production/Stable
Classifier: Intended Audience :: Developers
Classifier: Intended Audience :: Information Technology
Classifier: License :: OSI Approved :: MIT License
Classifier: Operating System :: OS Independent
Classifier: Programming Language :: Python :: 3
Classifier: Programming Language :: Python :: 3.10
Classifier: Programming Language :: Python :: 3.11
Classifier: Programming Language :: Python :: 3.12
Classifier: Programming Language :: Python :: 3.13
Classifier: Topic :: Security
Classifier: Topic :: Software Development :: Quality Assurance
Classifier: Topic :: Software Development :: Testing
Classifier: Topic :: Scientific/Engineering :: Artificial Intelligence
Classifier: Topic :: Internet :: WWW/HTTP :: Browsers
Requires-Python: >=3.10
Requires-Dist: fastmcp>=0.4.0
Requires-Dist: httpx>=0.27.0
Requires-Dist: pydantic>=2.0.0
Requires-Dist: typing-extensions>=4.0.0
Provides-Extra: dev
Requires-Dist: pytest>=7.0.0; extra == "dev"
Requires-Dist: pytest-asyncio>=0.21.0; extra == "dev"
Requires-Dist: black>=23.0.0; extra == "dev"
Requires-Dist: flake8>=6.0.0; extra == "dev"
Requires-Dist: mypy>=1.0.0; extra == "dev"
Provides-Extra: full
Requires-Dist: rich>=13.0.0; extra == "full"
Requires-Dist: colorama>=0.4.6; extra == "full"
Dynamic: author
Dynamic: home-page
Dynamic: maintainer
Dynamic: maintainer-email
Dynamic: platform
Dynamic: requires-python
